beekeeper/_bundle/__init__.py
beekeeper_ai-1.0.11.dist-info/METADATA
beekeeper_ai-1.0.11.dist-info/WHEEL
beekeeper_ai-1.0.11.dist-info/licenses/LICENSE
beekeeper_ai-1.0.11.dist-info/RECORD
