Metadata-Version: 2.4
Name: beekeeper-ai
Version: 1.0.11
Summary: Load any data in one line of code and connect with AI applications
Project-URL: Documentation, https://beekeeper-ai.github.io/beekeeper
Project-URL: Repository, https://github.com/beekeeper-ai/beekeeper
Author-email: Leonardo Furnielis <leonardofurnielis@outlook.com>
License: Apache-2.0
License-File: LICENSE
Keywords: AI,LLM,QA,RAG,data,observability,retrieval,semantic-search
Classifier: Topic :: Scientific/Engineering :: Artificial Intelligence
Classifier: Topic :: Software Development :: Libraries :: Application Frameworks
Classifier: Topic :: Software Development :: Libraries :: Python Modules
Requires-Python: <3.14,>=3.11
Requires-Dist: beekeeper-core<2.0.0,>=1.0.11
Requires-Dist: beekeeper-embeddings-huggingface<2.0.0,>=1.0.4
Requires-Dist: beekeeper-llms-litellm<2.0.0,>=1.0.3
Requires-Dist: beekeeper-readers-file<2.0.0,>=1.0.2
Provides-Extra: dev
Requires-Dist: ruff>=0.14.9; extra == 'dev'
